infra2conn/salesforce.py
infra2conn-0.0.3.dist-info/METADATA
infra2conn-0.0.3.dist-info/WHEEL
infra2conn-0.0.3.dist-info/entry_points.txt
infra2conn-0.0.3.dist-info/top_level.txt
infra2conn-0.0.3.dist-info/RECORD
